[
  {
    "id": 1,
    "priority": 1,
    "action": {
        "type" : "modifyHeaders",
        "responseHeaders": [{
            "header": "content-disposition",
            "operation": "set",
            "value": "inline;" 
        }]
    },
    "condition": {
      "urlFilter": "https://grnhse-use1-prod-s1-ghr.s3.amazonaws.com/person_attachments/*",
      "resourceTypes": [
        "main_frame",
        "sub_frame",
        "stylesheet",
        "script",
        "image",
        "font",
        "object",
        "xmlhttprequest",
        "ping",
        "csp_report",
        "media",
        "websocket",
        "webtransport",
        "webbundle",
        "other"
      ]
    }
  }
]
